jsonlibconfig/__init__.py
jsonlibconfig/decoder.py
jsonlibconfig/encoder.py
jsonlibconfig/lex.py
jsonlibconfig/yacc.py
jsonlibconfig-0.1.0.data/scripts/jsonlibconfig
jsonlibconfig-0.1.0.dist-info/LICENSE
jsonlibconfig-0.1.0.dist-info/METADATA
jsonlibconfig-0.1.0.dist-info/WHEEL
jsonlibconfig-0.1.0.dist-info/top_level.txt
jsonlibconfig-0.1.0.dist-info/RECORD
