Metadata-Version: 2.1
Name: jsonlibconfig
Version: 0.1.0
Summary: :sparkles: Pure python implementation library provides JSON <- convert -> Libconfig
Home-page: https://github.com/imZack/jsonlibconfig
Author: YuLun Shih
Author-email: shih@yulun.me
License: MIT
Platform: UNKNOWN
Classifier: Development Status :: 5 - Production/Stable
Classifier: Intended Audience :: Developers
Classifier: Natural Language :: English
Classifier: License :: OSI Approved :: MIT License
Classifier: Operating System :: OS Independent
Requires-Dist: ply
